[
    {
        "titulo": "Paredes se acercó al récord en un ratón empate ante Audax",
        "link": "http://chilenius.cl/paredes-se-acerco-al-record-en-un-raton-empate-ante-audax/",
        "fecha": "2018-10-28T19:47:10+00:00",
        "autor": "jtoro",
        "comentarios": "0"
    },
    {
        "titulo": "El King Arturo Vidal puso la manito en paliza del Barca al Real",
        "link": "http://chilenius.cl/el-king-arturo-vidal-puso-la-manito-en-paliza-del-barca-al-real/",
        "fecha": "2018-10-28T14:29:20+00:00",
        "autor": "jtoro",
        "comentarios": "0"
    },
    {
        "titulo": "Se prendió esta mierda: La U se afiló a la UC y quedó a 4 pts",
        "link": "http://chilenius.cl/se-prendio-esta-mierda-la-u-se-afilo-a-la-uc-y-quedo-a-4-pts/",
        "fecha": "2018-10-27T17:44:12+00:00",
        "autor": "jtoro",
        "comentarios": "0"
    },
    {
        "titulo": "El renacer de Henríquez y la cagá de Bose en triunfo azul",
        "link": "http://chilenius.cl/el-renacer-de-henriquez-y-la-caga-de-bose-en-triunfo-azul/",
        "fecha": "2018-10-21T22:12:10+00:00",
        "autor": "jtoro",
        "comentarios": "0"
    },
    {
        "titulo": "La mocha de la people por si Daniela Vega es hombre o mujer",
        "link": "http://chilenius.cl/la-mocha-de-la-people-por-si-daniela-vega-es-hombre-o-mujer/",
        "fecha": "2018-10-25T18:08:46+00:00",
        "autor": "jtoro",
        "comentarios": "0"
    },
    {
        "titulo": "Pillaron a viejo califa del Poder Judicial viendo porno en su ofi",
        "link": "http://chilenius.cl/pillaron-a-viejo-califa-del-poder-judicial-viendo-porno-en-su-ofi/",
        "fecha": "2018-10-24T13:40:03+00:00",
        "autor": "jtoro",
        "comentarios": "0"
    },
    {
        "titulo": "La férrea defensa a Javier Olivares por su acento y sobrepeso",
        "link": "http://chilenius.cl/la-ferrea-defensa-a-javier-olivares-por-su-acento-y-sobrepeso/",
        "fecha": "2018-10-22T14:02:10+00:00",
        "autor": "jtoro",
        "comentarios": "0"
    },
    {
        "titulo": "Tragedia: Al Viejito Pascuero de Chocolate lo mandaron a la B",
        "link": "http://chilenius.cl/tragedia-al-viejito-pascuero-de-chocolate-lo-mandaron-a-la-b/",
        "fecha": "2018-10-19T22:13:38+00:00",
        "autor": "jtoro",
        "comentarios": "0"
    },
    {
        "titulo": "El webeo pa grande a Sebastián Dávalos como Diezzel Kunst",
        "link": "http://chilenius.cl/el-webeo-pa-grande-a-sebastian-davalos-como-diezzel-kunst/",
        "fecha": "2018-10-18T13:22:35+00:00",
        "autor": "jtoro",
        "comentarios": "0"
    },
    {
        "titulo": "Los webiadores memes que dejó triunfo de Bolsonaro en Brasil",
        "link": "http://chilenius.cl/los-webiadores-memes-que-dejo-triunfo-de-bolsonaro-en-brasil/",
        "fecha": "2018-10-28T20:22:07+00:00",
        "autor": "jtoro",
        "comentarios": "0"
    },
    {
        "titulo": "Plan horripilante de niñas satánicas fue pillado por poli gringa",
        "link": "http://chilenius.cl/plan-horripilante-de-ninas-satanicas-fue-pillado-por-poli-gringa/",
        "fecha": "2018-10-25T11:21:27+00:00",
        "autor": "jtoro",
        "comentarios": "0"
    },
    {
        "titulo": "Viejuja califa pidió musculines para celebrar su cumple 89",
        "link": "http://chilenius.cl/viejuja-califa-pidio-musculines-para-celebrar-su-cumple-89/",
        "fecha": "2018-10-18T18:18:39+00:00",
        "autor": "jtoro",
        "comentarios": "0"
    },
    {
        "titulo": "El cagazo de Paul McCartney al confundir la bandera",
        "link": "http://chilenius.cl/el-cagazo-de-paul-mccartney-al-confundir-la-bandera/",
        "fecha": "2018-10-06T17:48:32+00:00",
        "autor": "jtoro",
        "comentarios": "0"
    },
    {
        "titulo": "Senador califa mexicano fue pillado chanchito en plena sesión",
        "link": "http://chilenius.cl/senador-califa-mexicano-fue-pillado-chanchito-en-plena-sesion/",
        "fecha": "2018-09-26T14:23:01+00:00",
        "autor": "jtoro",
        "comentarios": "0"
    },
    {
        "titulo": "La Soa Marisol nos tapó el hoci siendo finalista de BakeOff",
        "link": "http://chilenius.cl/la-soa-marisol-nos-tapo-el-hoci-siendo-finalista-de-bakeoff/",
        "fecha": "2018-10-28T23:32:25+00:00",
        "autor": "jtoro",
        "comentarios": "0"
    },
    {
        "titulo": "Esteban Araya se fue cagando de los cantantes de Rojo",
        "link": "http://chilenius.cl/esteban-araya-se-fue-cagando-de-los-cantantes-de-rojo/",
        "fecha": "2018-10-27T00:46:37+00:00",
        "autor": "jtoro",
        "comentarios": "0"
    },
    {
        "titulo": "La rabia y pena por el piteamiento del ecuatoriano Joel de Rojo",
        "link": "http://chilenius.cl/la-rabia-y-pena-por-el-piteamiento-del-ecuatoriano-joel-de-rojo/",
        "fecha": "2018-10-26T21:17:05+00:00",
        "autor": "jtoro",
        "comentarios": "0"
    },
    {
        "titulo": "Diana Bolocco y la Mali ayudaron a funar a gorda estafadora",
        "link": "http://chilenius.cl/diana-bolocco-y-la-mali-ayudaron-a-funar-a-gorda-estafadora/",
        "fecha": "2018-10-21T23:58:17+00:00",
        "autor": "jtoro",
        "comentarios": "0"
    },
    {
        "titulo": "Hermann pasó raspando con su Empire State piteandose a Isi",
        "link": "http://chilenius.cl/hermann-paso-raspando-con-su-empire-state-piteandose-a-isi/",
        "fecha": "2018-10-21T23:22:37+00:00",
        "autor": "jtoro",
        "comentarios": "0"
    },
    {
        "titulo": "Coqueteo Insípido: Los pelamientos más hot de farandulandia",
        "link": "http://chilenius.cl/coqueteo-insipido-los-pelamientos-mas-hot-de-farandulandia/",
        "fecha": "2018-08-22T10:43:37+00:00",
        "autor": "jtoro",
        "comentarios": "0"
    },
    {
        "titulo": "Otro más: Nuevo video filtrado muestra como afila Nelson Mauri!",
        "link": "http://chilenius.cl/otro-mas-nuevo-video-filtrado-muestra-como-afila-nelson-mauri/",
        "fecha": "2018-07-22T02:59:00+00:00",
        "autor": "jtoro",
        "comentarios": "0"
    },
    {
        "titulo": "Conmoción nacional por video “On fire” de Pato Laguna",
        "link": "http://chilenius.cl/conmocion-nacional-por-video-on-fire-de-pato-laguna/",
        "fecha": "2018-07-21T01:33:22+00:00",
        "autor": "jtoro",
        "comentarios": "0"
    },
    {
        "titulo": "Selfie en motel trajo una ola de frases en #UnaFraseDeMotel",
        "link": "http://chilenius.cl/selfie-en-motel-trajo-una-ola-de-frases-en-unafrasedemotel/",
        "fecha": "2018-10-20T22:37:45+00:00",
        "autor": "jtoro",
        "comentarios": "0"
    },
    {
        "titulo": "Hicieron cagar el infrahumano HT #NoSoyDonanteDeHaitianos",
        "link": "http://chilenius.cl/hicieron-cagar-el-infrahumano-ht-nosoydonantedehaitianos/",
        "fecha": "2018-09-30T20:25:36+00:00",
        "autor": "jtoro",
        "comentarios": "0"
    },
    {
        "titulo": "Las causas de las rabias de las mujeres en: #1MujerOdia",
        "link": "http://chilenius.cl/las-causas-de-las-rabias-de-las-mujeres-en-1mujerodia/",
        "fecha": "2018-09-01T20:45:25+00:00",
        "autor": "jtoro",
        "comentarios": "0"
    },
    {
        "titulo": "Twitter mató otra vez: Esta vez fue el turno de Isabel Allende",
        "link": "http://chilenius.cl/twitter-mato-otra-vez-esta-fue-el-turno-de-isabel-allende/",
        "fecha": "2018-08-22T13:38:52+00:00",
        "autor": "jtoro",
        "comentarios": "0"
    },
    {
        "titulo": "Cómo crear tu propio cuadro digital de Gokú Ultra Instinto!",
        "link": "http://chilenius.cl/como-crear-tu-propio-cuadro-digital-de-goku-ultra-instinto/",
        "fecha": "2018-08-12T15:23:47+00:00",
        "autor": "jtoro",
        "comentarios": "0"
    },
    {
        "titulo": "El esperado trailer de Dragon Ball Super: Broly hace de las suyas!",
        "link": "http://chilenius.cl/el-esperado-trailer-de-dragon-ball-super-broly-hace-de-las-suyas/",
        "fecha": "2018-07-20T02:47:30+00:00",
        "autor": "jtoro",
        "comentarios": "0"
    },
    {
        "titulo": "Dragon Ball Heroes ya lanzó su segundo mini capítulo!",
        "link": "http://chilenius.cl/dragon-ball-heroes-ya-lanzo-su-segundo-mini-capitulo/",
        "fecha": "2018-07-17T00:57:15+00:00",
        "autor": "jtoro",
        "comentarios": "0"
    },
    {
        "titulo": "La furia Twittera contra Karol Dance por exhibir a niño en Insta",
        "link": "http://chilenius.cl/la-furia-twittera-contra-karol-dance-por-exhibir-a-nino-en-insta/",
        "fecha": "2018-08-18T18:00:45+00:00",
        "autor": "jtoro",
        "comentarios": "0"
    },
    {
        "titulo": "El subnormal, neandertal, estúpido y peligroso “Kiki Challenge”",
        "link": "http://chilenius.cl/el-subnormal-neandertal-estupido-y-peligroso-kiki-challenge/",
        "fecha": "2018-08-02T14:44:06+00:00",
        "autor": "jtoro",
        "comentarios": "0"
    },
    {
        "titulo": "Cristiano Ronaldo aprovechó sus vacaciones para ir a China!",
        "link": "http://chilenius.cl/cristiano-ronaldo-aprovecho-sus-vacaciones-para-ir-a-china/",
        "fecha": "2018-07-29T04:25:11+00:00",
        "autor": "jtoro",
        "comentarios": "0"
    },
    {
        "titulo": "Día del Profesor: Los profes más recordados x la people",
        "link": "http://chilenius.cl/dia-del-profesor-los-profes-mas-recordados-x-la-people/",
        "fecha": "2018-10-16T13:57:52+00:00",
        "autor": "jtoro",
        "comentarios": "0"
    },
    {
        "titulo": "Primavera 2018: Los personajes relacionados con flores",
        "link": "http://chilenius.cl/primavera-2018-los-personajes-relacionados-con-flores/",
        "fecha": "2018-09-22T12:36:54+00:00",
        "autor": "jtoro",
        "comentarios": "0"
    },
    {
        "titulo": "Cómo bailar cueca a prueba de troncos como Lagos Weber",
        "link": "http://chilenius.cl/como-bailar-cueca-a-prueba-de-troncos-como-lagos-weber/",
        "fecha": "2018-09-04T14:38:54+00:00",
        "autor": "jtoro",
        "comentarios": "0"
    },
    {
        "titulo": "Los monitos animados que nos marcaron en los ’90",
        "link": "http://chilenius.cl/los-monitos-animados-que-nos-marcaron-en-los-90/",
        "fecha": "2018-08-29T14:10:33+00:00",
        "autor": "jtoro",
        "comentarios": "0"
    },
    {
        "titulo": "No tuviste infancia si no pasaste por estas weas",
        "link": "http://chilenius.cl/no-tuviste-infancia-si-no-pasaste-por-estas-weas/",
        "fecha": "2018-08-28T13:22:15+00:00",
        "autor": "jtoro",
        "comentarios": "0"
    },
    {
        "titulo": "Que no lo pillen volando bajo con estos tips diciocheros",
        "link": "http://chilenius.cl/que-no-lo-pillen-volando-bajo-con-estos-tips-diciocheros/",
        "fecha": "2018-09-10T13:50:29+00:00",
        "autor": "jtoro",
        "comentarios": "0"
    },
    {
        "titulo": "¿Cuántas calorías tiene el copete que toma en el carrete?",
        "link": "http://chilenius.cl/cuantas-calorias-tiene-el-copete-que-toma-en-el-carrete/",
        "fecha": "2018-08-17T13:16:44+00:00",
        "autor": "jtoro",
        "comentarios": "0"
    },
    {
        "titulo": "Los mejores consejos para que pueda “pasar Agosto”",
        "link": "http://chilenius.cl/los-mejores-consejos-para-que-pueda-pasar-agosto/",
        "fecha": "2018-08-06T14:13:20+00:00",
        "autor": "jtoro",
        "comentarios": "0"
    },
    {
        "titulo": "Sáquele la cresta al resfrío con estos remedios caseros",
        "link": "http://chilenius.cl/saquele-la-cresta-al-resfrio-con-estos-remedios-caseros/",
        "fecha": "2018-08-02T11:00:06+00:00",
        "autor": "jtoro",
        "comentarios": "0"
    },
    {
        "titulo": "¿Qué son los cálculos renales? Síntomas y tratamiento para usted",
        "link": "http://chilenius.cl/que-son-los-calculos-renales-sintomas-y-tratamiento-para-usted/",
        "fecha": "2018-08-01T17:45:41+00:00",
        "autor": "jtoro",
        "comentarios": "0"
    },
    {
        "titulo": "Simples consejos para que no lo caguen este CyberMonday",
        "link": "http://chilenius.cl/simples-consejos-para-que-no-lo-caguen-este-cybermonday/",
        "fecha": "2018-10-07T19:16:08+00:00",
        "autor": "jtoro",
        "comentarios": "0"
    },
    {
        "titulo": "86 millones de Neuronas según Herculano",
        "link": "http://chilenius.cl/86-millones-de-neuronas-segun-herculano/",
        "fecha": "2018-08-16T12:41:42+00:00",
        "autor": "Daniel Gutierrez",
        "comentarios": "0"
    },
    {
        "titulo": "Galaxy Note 9: Características de la nueva joyita de Samsung",
        "link": "http://chilenius.cl/galaxy-note-9-caracteristicas-de-la-nueva-joyita-de-samsung/",
        "fecha": "2018-08-12T14:03:51+00:00",
        "autor": "jtoro",
        "comentarios": "0"
    },
    {
        "titulo": "Cómo cambiar la hora en Android y Iphone a prueba de weones",
        "link": "http://chilenius.cl/como-cambiar-la-hora-en-android-y-iphone-a-prueba-de-weones/",
        "fecha": "2018-08-11T01:04:40+00:00",
        "autor": "jtoro",
        "comentarios": "2"
    },
    {
        "titulo": "RoboRatas – El Futuro es ahora Viejo !",
        "link": "http://chilenius.cl/roboratas-el-futuro-es-ahora-viejo/",
        "fecha": "2018-08-07T18:03:31+00:00",
        "autor": "Daniel Gutierrez",
        "comentarios": "0"
    },
    {
        "titulo": "Un nuevo Carnaval de Invierno se toma las calles de Punta Arenas",
        "link": "http://chilenius.cl/un-nuevo-carnaval-de-invierno-se-tomas-las-calles-de-punta-arenas/",
        "fecha": "2018-07-22T01:14:03+00:00",
        "autor": "jtoro",
        "comentarios": "0"
    },
    {
        "titulo": "Todo listo para la Fiesta de la Tirana 2018 en honor a la Virgen",
        "link": "http://chilenius.cl/todo-listo-para-la-fiesta-de-la-tirana-2018/",
        "fecha": "2018-07-16T04:50:51+00:00",
        "autor": "jtoro",
        "comentarios": "0"
    }
]